{
  "features": [
    "Ore",
    "WaterMill",
    "WaterZumpf",
    "PressureHC",
    "DensityHC",
    "MotorAmp",
    "Shisti",
    "Daiki"
  ],
  "target_col": "PSI80",
  "model_params": {
    "n_estimators": 300,
    "learning_rate": 0.05,
    "max_depth": 6,
    "subsample": 0.8,
    "colsample_bytree": 0.8,
    "early_stopping_rounds": 30,
    "objective": "reg:squarederror"
  },
  "feature_importance": {
    "Feature": {
      "4": "DensityHC",
      "0": "Ore",
      "2": "WaterZumpf",
      "1": "WaterMill",
      "7": "Daiki",
      "6": "Shisti",
      "3": "PressureHC",
      "5": "MotorAmp"
    },
    "Importance": {
      "4": 0.5350886583328247,
      "0": 0.12260662019252777,
      "2": 0.08935564756393433,
      "1": 0.08878105878829956,
      "7": 0.0450875386595726,
      "6": 0.042746759951114655,
      "3": 0.03951415792107582,
      "5": 0.03681952878832817
    }
  },
  "training_history": {
    "best_iteration": 299,
    "best_score": 0.22801352374195236
  },
  "timestamp": "20250707_115406"
}